django_occupations/__init__.py
django_occupations/admin.py
django_occupations/apps.py
django_occupations/models.py
django_occupations/populate_db.py
django_occupations/urls.py
django_occupations/management/commands/__init__.py
django_occupations/migrations/0001_initial.py
django_occupations/migrations/0002_add_soc_codes.py
django_occupations/migrations/0003_add_onet_models.py
django_occupations/migrations/0004_add_name_to_sochighlevel.py
django_occupations/migrations/0005_make_alttitle_to_occupation_m2m_part1.py
django_occupations/migrations/0006_make_alttitle_to_occupation_m2m_part2.py
django_occupations/migrations/0007_make_alttitle_to_occupation_m2m_part3.py
django_occupations/migrations/__init__.py
django_occupations/templates/django_occupations/base.html
django_occupations-0.2.2.dist-info/LICENSE.txt
django_occupations-0.2.2.dist-info/METADATA
django_occupations-0.2.2.dist-info/WHEEL
django_occupations-0.2.2.dist-info/top_level.txt
django_occupations-0.2.2.dist-info/RECORD
