Metadata-Version: 2.1
Name: django-occupations
Version: 0.2.2
Summary: A reusable Django App for importing, updating, and managing structured occupation data.
Home-page: https://github.com/CareerVillage/django-occupations
Author: CareerVillage
Author-email: hello@careervillage.org
License: Apache Software License 2.0
Keywords: Python occupations
Platform: UNKNOWN
Classifier: Development Status :: 3 - Alpha
Classifier: Framework :: Django
Classifier: Framework :: Django :: 3.0
Classifier: Framework :: Django :: 3.1
Classifier: Intended Audience :: Developers
Classifier: License :: OSI Approved :: Apache Software License
Classifier: Natural Language :: English
Classifier: Programming Language :: Python :: 3
Classifier: Programming Language :: Python :: 3.5
Classifier: Programming Language :: Python :: 3.8
Requires-Python: >=3.5
Requires-Dist: Django (>=1.11)
Requires-Dist: django-model-utils
